{
  "stats": {
    "total_shifts": 8446,
    "shifts_by_weekday": {
      "Mon": 1499,
      "Tue": 1332,
      "Wed": 1201,
      "Thu": 1232,
      "Fri": 1628,
      "Sat": 1554,
      "Sun": 0
    },
    "block_type_counts": {
      "2er": 6097,
      "3er": 1852,
      "1er": 497
    }
  },
  "target_block_mix_overall": {
    "1er": 0.059,
    "2er": 0.722,
    "3er": 0.219
  },
  "target_block_mix_by_weekday": {
    "Mon": {
      "1er": 0.032,
      "2er": 0.733,
      "3er": 0.235
    },
    "Tue": {
      "1er": 0.042,
      "2er": 0.776,
      "3er": 0.182
    },
    "Wed": {
      "1er": 0.053,
      "2er": 0.744,
      "3er": 0.202
    },
    "Thu": {
      "1er": 0.045,
      "2er": 0.781,
      "3er": 0.174
    },
    "Fri": {
      "1er": 0.02,
      "2er": 0.642,
      "3er": 0.338
    },
    "Sat": {
      "1er": 0.155,
      "2er": 0.684,
      "3er": 0.161
    },
    "Sun": {
      "1er": 0.0,
      "2er": 0.0,
      "3er": 0.0
    }
  },
  "split2_rate_overall": 0.366,
  "split2_rate_by_weekday": {
    "Mon": 0.449,
    "Tue": 0.409,
    "Wed": 0.372,
    "Thu": 0.369,
    "Fri": 0.385,
    "Sat": 0.209,
    "Sun": 0.0
  },
  "gap_modes": [
    60,
    45,
    30,
    75,
    330,
    375,
    405,
    390,
    360,
    315
  ],
  "gap_histogram": {
    "60": 3597,
    "45": 1899,
    "30": 1292,
    "75": 440,
    "330": 199,
    "375": 189,
    "405": 187,
    "390": 175,
    "360": 168,
    "315": 161,
    "420": 137,
    "90": 133,
    "345": 131,
    "435": 118,
    "465": 105,
    "450": 91,
    "300": 83,
    "270": 81,
    "285": 75,
    "120": 62
  },
  "split_gap_cluster": {
    "min": 180,
    "max": 555,
    "count": 2229
  },
  "canonical_windows_overall": [
    "05:00-09:30",
    "15:00-19:30",
    "04:45-09:15",
    "05:15-09:45",
    "06:00-10:30",
    "06:15-10:45",
    "14:45-19:15",
    "05:45-10:15",
    "16:00-20:30",
    "05:30-10:00",
    "09:00-13:30",
    "14:00-18:30",
    "14:15-18:45",
    "18:00-22:30",
    "14:30-19:00",
    "08:30-13:00",
    "08:15-12:45",
    "15:15-19:45",
    "17:00-21:30",
    "08:45-13:15",
    "08:00-12:30",
    "09:15-13:45",
    "12:00-16:30",
    "18:30-23:00",
    "17:15-21:45",
    "11:45-16:15",
    "13:00-17:30",
    "16:15-20:45",
    "10:30-15:00",
    "17:45-22:15",
    "07:00-11:30",
    "07:45-12:15",
    "15:45-20:15",
    "10:00-14:30",
    "06:30-11:00",
    "09:30-14:00",
    "13:45-18:15",
    "17:30-22:00",
    "10:45-15:15",
    "12:30-17:00",
    "12:45-17:15",
    "18:15-22:45",
    "06:45-11:15",
    "13:15-17:45",
    "12:15-16:45",
    "10:15-14:45",
    "11:30-16:00",
    "15:30-20:00",
    "13:30-18:00",
    "16:45-21:15",
    "07:15-11:45",
    "09:45-14:15",
    "07:30-12:00",
    "11:00-15:30",
    "16:30-21:00",
    "11:15-15:45",
    "05:45-10:30",
    "07:45-12:45",
    "05:00-10:00",
    "12:00-17:00"
  ],
  "canonical_windows_by_weekday": {
    "Mon": [
      "05:15-09:45",
      "04:45-09:15",
      "05:00-09:30",
      "05:45-10:15",
      "05:30-10:00",
      "15:00-19:30",
      "06:15-10:45",
      "06:00-10:30",
      "09:00-13:30",
      "14:15-18:45",
      "14:45-19:15",
      "14:00-18:30",
      "16:00-20:30",
      "18:30-23:00",
      "14:30-19:00",
      "17:45-22:15",
      "17:00-21:30",
      "18:00-22:30",
      "09:15-13:45",
      "08:15-12:45",
      "08:45-13:15",
      "07:45-12:15",
      "13:45-18:15",
      "18:15-22:45",
      "08:30-13:00",
      "17:15-21:45",
      "10:45-15:15",
      "17:30-22:00",
      "10:30-15:00",
      "11:00-15:30",
      "15:15-19:45",
      "16:45-21:15",
      "16:15-20:45",
      "11:45-16:15",
      "07:30-12:00",
      "13:30-18:00",
      "11:30-16:00",
      "10:00-14:30",
      "15:45-20:15",
      "11:15-15:45"
    ],
    "Tue": [
      "05:00-09:30",
      "04:45-09:15",
      "05:15-09:45",
      "06:15-10:45",
      "15:00-19:30",
      "16:00-20:30",
      "14:15-18:45",
      "06:00-10:30",
      "14:45-19:15",
      "14:00-18:30",
      "18:30-23:00",
      "05:30-10:00",
      "05:45-10:15",
      "18:00-22:30",
      "09:15-13:45",
      "08:45-13:15",
      "09:00-13:30",
      "17:00-21:30",
      "18:15-22:45",
      "17:30-22:00",
      "17:45-22:15",
      "08:30-13:00",
      "14:30-19:00",
      "13:15-17:45",
      "16:15-20:45",
      "15:15-19:45",
      "12:00-16:30",
      "09:30-14:00",
      "17:15-21:45",
      "08:15-12:45",
      "11:45-16:15",
      "08:00-12:30",
      "10:45-15:15",
      "13:00-17:30",
      "12:45-17:15",
      "06:30-11:00",
      "12:15-16:45",
      "09:45-14:15",
      "07:45-12:15",
      "12:30-17:00"
    ],
    "Wed": [
      "05:00-09:30",
      "05:15-09:45",
      "15:00-19:30",
      "04:45-09:15",
      "06:00-10:30",
      "06:15-10:45",
      "14:45-19:15",
      "17:15-21:45",
      "16:00-20:30",
      "18:00-22:30",
      "17:00-21:30",
      "13:00-17:30",
      "08:30-13:00",
      "14:15-18:45",
      "05:45-10:15",
      "05:30-10:00",
      "16:45-21:15",
      "14:00-18:30",
      "12:45-17:15",
      "13:15-17:45",
      "11:45-16:15",
      "17:30-22:00",
      "17:45-22:15",
      "18:15-22:45",
      "08:00-12:30",
      "10:30-15:00",
      "09:30-14:00",
      "18:30-23:00",
      "13:30-18:00",
      "10:15-14:45",
      "14:30-19:00",
      "08:45-13:15",
      "09:00-13:30",
      "10:45-15:15",
      "09:45-14:15",
      "08:15-12:45",
      "12:30-17:00",
      "09:15-13:45",
      "07:30-12:00",
      "16:30-21:00"
    ],
    "Thu": [
      "05:00-09:30",
      "15:00-19:30",
      "04:45-09:15",
      "06:00-10:30",
      "09:00-13:30",
      "05:15-09:45",
      "06:15-10:45",
      "18:00-22:30",
      "08:15-12:45",
      "05:45-10:15",
      "17:00-21:30",
      "05:30-10:00",
      "15:15-19:45",
      "14:45-19:15",
      "14:15-18:45",
      "14:00-18:30",
      "08:00-12:30",
      "17:45-22:15",
      "15:45-20:15",
      "09:15-13:45",
      "16:00-20:30",
      "17:15-21:45",
      "13:45-18:15",
      "18:15-22:45",
      "11:45-16:15",
      "12:45-17:15",
      "13:00-17:30",
      "08:45-13:15",
      "14:30-19:00",
      "08:30-13:00",
      "12:00-16:30",
      "07:45-12:15",
      "12:30-17:00",
      "10:30-15:00",
      "17:30-22:00",
      "12:15-16:45",
      "16:15-20:45",
      "13:30-18:00",
      "18:30-23:00",
      "09:30-14:00"
    ],
    "Fri": [
      "15:00-19:30",
      "04:45-09:15",
      "05:15-09:45",
      "05:00-09:30",
      "06:00-10:30",
      "06:15-10:45",
      "18:00-22:30",
      "16:00-20:30",
      "07:00-11:30",
      "05:45-10:15",
      "14:45-19:15",
      "17:00-21:30",
      "15:15-19:45",
      "14:30-19:00",
      "16:15-20:45",
      "08:30-13:00",
      "10:30-15:00",
      "13:00-17:30",
      "05:30-10:00",
      "17:15-21:45",
      "08:45-13:15",
      "07:45-12:15",
      "12:00-16:30",
      "18:30-23:00",
      "15:30-20:00",
      "13:45-18:15",
      "09:00-13:30",
      "16:45-21:15",
      "08:00-12:30",
      "17:30-22:00",
      "06:45-11:15",
      "10:45-15:15",
      "14:00-18:30",
      "10:00-14:30",
      "13:15-17:45",
      "12:30-17:00",
      "06:30-11:00",
      "11:30-16:00",
      "10:15-14:45",
      "11:00-15:30"
    ],
    "Sat": [
      "15:00-19:30",
      "05:00-09:30",
      "06:00-10:30",
      "14:45-19:15",
      "05:45-10:15",
      "06:30-11:00",
      "06:15-10:45",
      "04:45-09:15",
      "05:15-09:45",
      "07:00-11:30",
      "06:45-11:15",
      "07:15-11:45",
      "08:15-12:45",
      "05:30-10:00",
      "08:00-12:30",
      "15:15-19:45",
      "12:00-16:30",
      "10:00-14:30",
      "09:45-14:15",
      "12:15-16:45",
      "08:30-13:00",
      "14:30-19:00",
      "10:15-14:45",
      "15:45-20:15",
      "16:00-20:30",
      "12:30-17:00",
      "09:00-13:30",
      "14:00-18:30",
      "08:45-13:15",
      "09:30-14:00",
      "11:45-16:15",
      "11:30-16:00",
      "07:30-12:00",
      "13:00-17:30",
      "15:30-20:00",
      "07:45-12:15",
      "16:15-20:45",
      "14:15-18:45",
      "12:45-17:15",
      "16:30-21:00"
    ],
    "Sun": []
  },
  "top_pair_templates": [
    "06:15-10:45/11:45-16:15",
    "09:00-13:30/14:30-19:00",
    "08:45-13:15/14:15-18:45",
    "08:30-13:00/14:00-18:30",
    "09:30-14:00/15:00-19:30",
    "09:15-13:45/14:45-19:15",
    "08:15-12:45/13:45-18:15",
    "06:30-11:00/12:00-16:30",
    "09:00-13:30/14:15-18:45",
    "08:00-12:30/13:30-18:00",
    "06:45-11:15/12:15-16:45",
    "05:00-09:30/15:00-19:30",
    "07:00-11:30/12:30-17:00",
    "06:00-10:30/11:30-16:00",
    "07:45-12:15/13:15-17:45",
    "08:45-13:15/14:00-18:30",
    "13:15-17:45/18:30-23:00",
    "12:30-17:00/18:00-22:30",
    "09:15-13:45/15:00-19:30",
    "06:00-10:30/17:15-21:45",
    "12:45-17:15/18:15-22:45",
    "05:00-09:30/15:45-20:15",
    "04:45-09:15/09:45-14:15",
    "05:00-09:30/10:30-15:00",
    "08:45-13:15/14:30-19:00",
    "04:45-09:15/15:00-19:30",
    "07:15-11:45/12:45-17:15",
    "05:00-09:30/16:00-20:30",
    "13:00-17:30/18:00-22:30",
    "08:30-13:00/13:45-18:15",
    "09:15-13:45/14:30-19:00",
    "13:00-17:30/18:30-23:00",
    "09:30-14:00/14:45-19:15",
    "09:00-13:30/14:45-19:15",
    "13:30-18:00/18:30-23:00",
    "05:15-09:45/15:15-19:45",
    "05:45-10:15/17:00-21:30",
    "06:00-10:30/17:00-21:30",
    "06:15-10:45/17:30-22:00",
    "08:30-13:00/14:15-18:45",
    "07:30-12:00/13:00-17:30",
    "06:45-11:15/12:00-16:30",
    "05:45-10:15/11:15-15:45",
    "05:15-09:45/17:00-21:30",
    "04:45-09:15/15:15-19:45",
    "05:00-09:30/14:00-18:30",
    "05:15-09:45/15:00-19:30",
    "08:15-12:45/13:30-18:00",
    "05:30-10:00/17:45-22:15",
    "08:15-12:45/14:00-18:30",
    "06:00-10:30/17:30-22:00",
    "12:45-17:15/18:00-22:30",
    "13:00-17:30/18:15-22:45",
    "06:15-10:45/17:00-21:30",
    "08:00-12:30/13:45-18:15",
    "07:00-11:30/12:15-16:45",
    "09:00-13:30/15:00-19:30",
    "06:15-10:45/18:00-22:30",
    "05:15-09:45/16:45-21:15",
    "08:30-13:00/14:30-19:00",
    "05:30-10:00/17:00-21:30",
    "05:45-10:15/17:15-21:45",
    "05:15-09:45/16:15-20:45",
    "05:00-09:30/14:45-19:15",
    "06:15-10:45/17:15-21:45",
    "08:00-12:30/13:15-17:45",
    "07:45-12:15/13:30-18:00",
    "05:30-10:00/11:00-15:30",
    "06:15-10:45/12:00-16:30",
    "06:15-10:45/16:00-20:30",
    "12:15-16:45/17:45-22:15",
    "07:00-11:30/12:00-16:30",
    "05:15-09:45/17:30-22:00",
    "06:15-10:45/17:45-22:15",
    "05:15-09:45/17:15-21:45",
    "09:30-14:00/15:15-19:45",
    "05:45-10:15/17:30-22:00",
    "06:00-10:30/16:00-20:30",
    "06:00-10:30/17:45-22:15",
    "05:15-09:45/10:45-15:15",
    "07:30-12:00/18:00-22:30",
    "05:15-09:45/16:00-20:30",
    "05:45-10:15/18:00-22:30",
    "09:00-13:30/14:00-18:30",
    "05:30-10:00/15:15-19:45",
    "07:45-12:15/12:45-17:15",
    "08:45-13:15/14:45-19:15",
    "05:15-09:45/15:45-20:15",
    "08:00-12:30/13:00-17:30",
    "07:45-12:15/13:45-18:15",
    "05:30-10:00/17:30-22:00",
    "08:30-13:00/16:30-21:00",
    "04:45-09:15/10:00-14:30",
    "07:45-12:15/18:15-22:45",
    "08:15-12:45/14:45-19:15",
    "04:45-09:15/10:15-14:45",
    "05:00-09:30/15:15-19:45",
    "06:00-10:30/11:45-16:15",
    "05:00-09:30/16:15-20:45",
    "06:00-10:30/18:00-22:30"
  ],
  "top_triple_templates": [
    "04:45-09:15/09:45-14:15/14:45-19:15",
    "05:15-09:45/10:45-15:15/16:00-20:30",
    "06:00-10:30/11:30-16:00/17:00-21:30",
    "04:45-09:15/10:00-14:30/15:00-19:30",
    "05:00-09:30/10:30-15:00/16:00-20:30",
    "04:45-09:15/10:00-14:30/15:15-19:45",
    "05:00-09:30/10:00-14:30/15:00-19:30",
    "05:45-10:15/11:15-15:45/16:45-21:15",
    "04:45-09:15/10:15-14:45/15:30-20:00",
    "05:15-09:45/10:45-15:15/16:15-20:45",
    "05:30-10:00/11:00-15:30/16:15-20:45",
    "05:00-09:30/10:30-15:00/15:45-20:15",
    "04:45-09:15/09:45-14:15/15:00-19:30",
    "06:00-10:30/11:30-16:00/16:45-21:15",
    "05:30-10:00/11:00-15:30/16:30-21:00",
    "04:45-09:15/10:15-14:45/15:15-19:45",
    "05:00-09:30/10:15-14:45/15:15-19:45",
    "05:45-10:15/11:15-15:45/16:30-21:00",
    "05:00-09:30/10:15-14:45/15:45-20:15",
    "05:30-10:00/11:00-15:30/16:00-20:30",
    "08:00-12:30/13:15-17:45/18:30-23:00",
    "07:45-12:15/13:15-17:45/18:30-23:00",
    "04:45-09:15/10:15-14:45/15:45-20:15",
    "05:00-09:30/10:15-14:45/15:30-20:00",
    "05:30-10:00/10:45-15:15/16:00-20:30",
    "05:15-09:45/10:15-14:45/15:15-19:45",
    "05:00-09:30/10:30-15:00/15:30-20:00",
    "05:15-09:45/10:30-15:00/15:30-20:00",
    "04:45-09:15/10:00-14:30/15:30-20:00",
    "05:45-10:15/11:00-15:30/16:15-20:45",
    "07:30-12:00/12:45-17:15/18:15-22:45",
    "05:45-10:15/11:15-15:45/16:15-20:45",
    "06:30-11:00/12:00-16:30/17:15-21:45",
    "07:30-12:00/12:45-17:15/18:00-22:30",
    "07:15-11:45/12:45-17:15/18:00-22:30",
    "06:00-10:30/11:30-16:00/16:30-21:00",
    "07:00-11:30/12:30-17:00/18:00-22:30",
    "05:30-10:00/10:30-15:00/15:30-20:00",
    "08:00-12:30/13:00-17:30/18:00-22:30",
    "07:00-11:30/12:30-17:00/17:45-22:15",
    "05:15-09:45/10:30-15:00/16:00-20:30",
    "05:15-09:45/10:30-15:00/15:45-20:15",
    "07:30-12:00/13:00-17:30/18:00-22:30",
    "06:15-10:45/11:45-16:15/17:00-21:30",
    "07:00-11:30/12:15-16:45/17:30-22:00",
    "07:30-12:00/13:00-17:30/18:15-22:45",
    "07:45-12:15/13:00-17:30/18:30-23:00",
    "06:15-10:45/11:45-16:15/17:15-21:45",
    "05:15-09:45/10:45-15:15/15:45-20:15",
    "07:15-11:45/12:00-16:30/17:30-22:00",
    "05:00-09:30/10:30-15:00/16:15-20:45",
    "05:00-09:30/10:00-14:30/15:15-19:45",
    "06:00-10:30/11:15-15:45/16:30-21:00",
    "07:45-12:15/13:00-17:30/18:00-22:30",
    "05:30-10:00/10:30-15:00/16:00-20:30",
    "06:45-11:15/12:15-16:45/17:30-22:00",
    "05:45-10:15/11:00-15:30/16:30-21:00",
    "07:30-12:00/12:30-17:00/18:00-22:30",
    "07:45-12:15/13:00-17:30/18:15-22:45",
    "05:30-10:00/10:45-15:15/15:45-20:15",
    "07:00-11:30/12:15-16:45/17:15-21:45",
    "07:15-11:45/12:15-16:45/17:30-22:00",
    "08:00-12:30/13:30-18:00/18:30-23:00",
    "05:45-10:15/10:45-15:15/15:45-20:15",
    "07:00-11:30/12:00-16:30/17:15-21:45",
    "07:15-11:45/12:45-17:15/18:15-22:45",
    "05:15-09:45/10:15-14:45/15:30-20:00",
    "05:45-10:15/11:00-15:30/16:00-20:30",
    "06:45-11:15/12:15-16:45/17:45-22:15",
    "08:00-12:30/13:15-17:45/18:15-22:45",
    "06:00-10:30/11:15-15:45/16:45-21:15",
    "04:45-09:15/09:45-14:15/14:00-18:30",
    "07:45-12:15/13:15-17:45/18:15-22:45",
    "05:45-10:15/10:45-15:15/16:00-20:30",
    "06:30-11:00/11:45-16:15/17:00-21:30",
    "07:15-11:45/12:15-16:45/17:15-21:45",
    "07:30-12:00/13:00-17:30/18:30-23:00",
    "08:00-12:30/13:00-17:30/18:15-22:45",
    "07:00-11:30/12:00-16:30/17:30-22:00",
    "05:30-10:00/10:45-15:15/16:30-21:00",
    "06:00-10:30/11:30-16:00/17:15-21:45",
    "07:45-12:15/12:45-17:15/17:45-22:15",
    "06:15-10:45/11:30-16:00/16:45-21:15",
    "07:00-11:30/12:45-17:15/18:15-22:45",
    "08:00-12:30/13:00-17:30/18:30-23:00",
    "06:30-11:00/11:30-16:00/16:45-21:15",
    "05:15-09:45/10:30-15:00/16:15-20:45",
    "06:30-11:00/11:30-16:00/16:30-21:00",
    "05:45-10:15/11:00-15:30/16:45-21:15",
    "06:45-11:15/12:00-16:30/17:15-21:45",
    "07:15-11:45/12:30-17:00/17:45-22:15",
    "06:00-10:30/11:15-15:45/16:15-20:45",
    "06:30-11:00/12:00-16:30/17:30-22:00",
    "07:45-12:15/12:45-17:15/18:15-22:45",
    "07:00-11:30/12:15-16:45/17:45-22:15",
    "05:45-10:15/11:15-15:45/17:00-21:30",
    "06:30-11:00/11:30-16:00/17:00-21:30",
    "06:45-11:15/11:45-16:15/17:15-21:45",
    "05:30-10:00/10:45-15:15/16:15-20:45",
    "07:00-11:30/12:00-17:00/18:00-22:30"
  ]
}